pscheduler/__init__.py
pscheduler/checkCPUusage.py
pscheduler/parser.py
pscheduler/pdaemon.py
pscheduler/phosts.py
pscheduler/pjobs.py
pscheduler/psub.py
pscheduler-0.1.0.data/scripts/batchSetupLoginKeys.py
pscheduler-0.1.0.data/scripts/bhostsWrapper.py
pscheduler-0.1.0.data/scripts/pscheduler
pscheduler-0.1.0.dist-info/DESCRIPTION.rst
pscheduler-0.1.0.dist-info/METADATA
pscheduler-0.1.0.dist-info/RECORD
pscheduler-0.1.0.dist-info/WHEEL
pscheduler-0.1.0.dist-info/metadata.json
pscheduler-0.1.0.dist-info/top_level.txt
