Metadata-Version: 2.0
Name: pscheduler
Version: 0.1.0
Summary: A pure Python remote job scheduler system
Home-page: https://github.com/parashardhapola/pscheduler
Author: Parashar Dhapola
Author-email: parashar.dhapola@gmail.com
License: MIT
Download-URL: https://github.com/parashardhapola/pscheduler/tarball/0.1.0
Keywords: scheduler
Platform: UNKNOWN
Classifier: Development Status :: 4 - Beta
Classifier: License :: OSI Approved :: MIT License
Classifier: Natural Language :: English
Classifier: Operating System :: POSIX :: Linux
Classifier: Programming Language :: Python :: 3
Classifier: Programming Language :: Python :: 3.5
Classifier: Topic :: System :: Distributed Computing
Requires-Dist: psutil
Requires-Dist: terminaltables
